setup.py
shelve.py
micropython_shelve.egg-info/PKG-INFO
micropython_shelve.egg-info/SOURCES.txt
micropython_shelve.egg-info/dependency_links.txt
micropython_shelve.egg-info/top_level.txt