Metadata-Version: 1.0
Name: micropython-shelve
Version: 0.0.0
Summary: Dummy shelve module for MicroPython
Home-page: https://github.com/micropython/micropython/issues/405
Author: MicroPython Developers
Author-email: micro-python@googlegroups.com
License: MIT
Platform: UNKNOWN
